recon/__init__.py
recon/__main__.py
recon/main.py
recon/reconcile.py
recon/utils.py
recon_cli-0.0.5.dist-info/entry_points.txt
recon_cli-0.0.5.dist-info/LICENSE.txt
recon_cli-0.0.5.dist-info/WHEEL
recon_cli-0.0.5.dist-info/METADATA
recon_cli-0.0.5.dist-info/RECORD
