Metadata-Version: 2.1
Name: recon-cli
Version: 0.0.5
Summary: Simple command line tool to reconcile datasets
Author-email: Mynhardt Burger <mynhardt+recon@gmail.com>
Requires-Python: >=3.9
Classifier: Programming Language :: Python :: 3
Classifier: License :: OSI Approved :: MIT License
Classifier: Operating System :: OS Independent
Classifier: Intended Audience :: Financial and Insurance Industry
Classifier: Natural Language :: English
Requires-Dist: pandas == 2.0.1
Requires-Dist: pandas[performance] == 2.0.1
Requires-Dist: pandas[excel] == 2.0.1
Requires-Dist: typer[all] == 0.9.0
Requires-Dist: pytest >=2.7.3 ; extra == "test"
Requires-Dist: pytest-cov ; extra == "test"
Project-URL: Homepage, https://github.com/mynhardtburger/recon-cli
Provides-Extra: test
